opensr_srgan/__init__.py
opensr_srgan/_factory.py
opensr_srgan/inference.py
opensr_srgan/train.py
opensr_srgan/configs/config_10m.yaml
opensr_srgan/configs/config_20m.yaml
opensr_srgan/configs/config_playgound.yaml
opensr_srgan/data/__init__.py
opensr_srgan/data/dataset_selector.py
opensr_srgan/data/example_data/download_example_dataset.py
opensr_srgan/data/example_data/example_dataset.py
opensr_srgan/data/sen2_test/sen2_test_dataset.py
opensr_srgan/data/sen2_test/test_step.py
opensr_srgan/data/utils/__init__.py
opensr_srgan/data/utils/normalizer.py
opensr_srgan/model/SRGAN.py
opensr_srgan/model/__init__.py
opensr_srgan/model/training_step_PL.py
opensr_srgan/model/discriminators/__init__.py
opensr_srgan/model/discriminators/esrgan.py
opensr_srgan/model/discriminators/patchgan.py
opensr_srgan/model/discriminators/srgan_discriminator.py
opensr_srgan/model/generators/SRGAN_advanced.py
opensr_srgan/model/generators/__init__.py
opensr_srgan/model/generators/cgan_generator.py
opensr_srgan/model/generators/esrgan.py
opensr_srgan/model/generators/factory.py
opensr_srgan/model/generators/flexible_generator.py
opensr_srgan/model/generators/srresnet.py
opensr_srgan/model/loss/__init__.py
opensr_srgan/model/loss/loss.py
opensr_srgan/model/loss/vgg.py
opensr_srgan/model/model_blocks/EMA.py
opensr_srgan/model/model_blocks/__init__.py
opensr_srgan/tests/test_version.py
opensr_srgan/tests/helpers/__init__.py
opensr_srgan/tests/helpers/custom_norms.py
opensr_srgan/tests/test_data/test_dataset_selector.py
opensr_srgan/tests/test_data/test_normalizer.py
opensr_srgan/tests/test_loss/test_loss.py
opensr_srgan/tests/test_loss/test_vgg.py
opensr_srgan/tests/test_model_blocks/test_ema.py
opensr_srgan/tests/test_models/test_discriminators.py
opensr_srgan/tests/test_models/test_generators.py
opensr_srgan/tests/test_models/test_model_creation.py
opensr_srgan/tests/test_utils/test_gpu_rank.py
opensr_srgan/tests/test_utils/test_model_descriptor.py
opensr_srgan-0.3.0.dist-info/licenses/LICENSE
opensr_srgan-0.3.0.dist-info/METADATA
opensr_srgan-0.3.0.dist-info/WHEEL
opensr_srgan-0.3.0.dist-info/top_level.txt
opensr_srgan-0.3.0.dist-info/RECORD
