Metadata-Version: 2.4
Name: opensr-srgan
Version: 0.3.0
Summary: Modular Super-Resolution GAN Framework for Remote Sensing.
Author: Simon Donike, ESAOpenSR Team
License:                                  Apache License
Project-URL: Homepage, https://github.com/opensr-project/SISR-RS-SRGAN
Project-URL: Documentation, https://srgan.opensr.eu
Project-URL: Bug Tracker, https://github.com/opensr-project/SISR-RS-SRGAN/issues
Keywords: super-resolution,gan,remote-sensing,pytorch,lightning
Classifier: Programming Language :: Python
Classifier: Programming Language :: Python :: 3.10
Classifier: License :: OSI Approved :: MIT License
Classifier: Intended Audience :: Science/Research
Classifier: Topic :: Scientific/Engineering :: Artificial Intelligence
Requires-Python: !=3.11.*,<3.13,>=3.10
License-File: LICENSE
Requires-Dist: torch==1.13.1; python_version < "3.11"
Requires-Dist: torch>=2.1; python_version >= "3.12"
Requires-Dist: pytorch-lightning==1.9.*; python_version < "3.11"
Requires-Dist: pytorch-lightning<3.0,>=2.1; python_version >= "3.12"
Requires-Dist: torchvision
Requires-Dist: numpy
Requires-Dist: kornia
Requires-Dist: wandb
Requires-Dist: omegaconf
Requires-Dist: matplotlib
Requires-Dist: rasterio
Requires-Dist: scikit-image
Requires-Dist: Pillow
Requires-Dist: huggingface-hub
Provides-Extra: tests
Requires-Dist: pytest; extra == "tests"
Requires-Dist: pytest-cov; extra == "tests"
Requires-Dist: numpy; extra == "tests"
Provides-Extra: docs
Requires-Dist: mkdocs-material; extra == "docs"
Dynamic: license-file
